perforatedbp/__init__.cpython-311-darwin.so
perforatedbp/blockwise_pbp.cpython-311-darwin.so
perforatedbp/check_license.cpython-311-darwin.so
perforatedbp/clean_load.cpython-311-darwin.so
perforatedbp/globals_pbp.cpython-311-darwin.so
perforatedbp/modules_pbp.cpython-311-darwin.so
perforatedbp/network_pbp.cpython-311-darwin.so
perforatedbp/tracker_pbp.cpython-311-darwin.so
perforatedbp/utils_pbp.cpython-311-darwin.so
perforatedbp-3.0.7.dist-info/METADATA
perforatedbp-3.0.7.dist-info/WHEEL
perforatedbp-3.0.7.dist-info/top_level.txt
perforatedbp-3.0.7.dist-info/RECORD
