Metadata-Version: 2.1
Name: perforatedbp
Version: 3.0.7
Summary: perforatedai perforatedbp package
Author: PerforatedAI
Author-email: rorry@perforatedai.com
License: This software may only be used by getting a license from PerforatedAI.com and agreeing to the terms and conditions
Requires-Python: >=3.6
Requires-Dist: torch
Requires-Dist: torchvision
Requires-Dist: matplotlib
Requires-Dist: pandas
Requires-Dist: rsa
Requires-Dist: pyyaml
Requires-Dist: safetensors
